liquorice-0.1.0-py3.7-nspkg.pth
liquorice/core/__init__.py
liquorice/core/const.py
liquorice/core/database.py
liquorice/core/exceptions.py
liquorice/core/tasks.py
liquorice/worker/__init__.py
liquorice/worker/dispatcher.py
liquorice/worker/runner.py
liquorice/worker/threading.py
liquorice/worker/worker.py
liquorice-0.1.0.dist-info/LICENSE
liquorice-0.1.0.dist-info/METADATA
liquorice-0.1.0.dist-info/WHEEL
liquorice-0.1.0.dist-info/namespace_packages.txt
liquorice-0.1.0.dist-info/top_level.txt
liquorice-0.1.0.dist-info/RECORD
