Metadata-Version: 2.1
Name: liquorice
Version: 0.1.0
Summary: PostgreSQL-backed generic task queue for async Python
Home-page: https://github.com/ghost-of-turek/liQuorice
Author: Artur Ciesielski
Author-email: artur.ciesielski@gmail.com
License: MIT
Keywords: async,queue,task,job,postgres
Platform: UNKNOWN
Classifier: Development Status :: 1 - Planning
Classifier: Intended Audience :: Developers
Classifier: License :: OSI Approved :: MIT License
Classifier: Natural Language :: English
Classifier: Programming Language :: Python :: 3.7
Classifier: Programming Language :: Python :: 3.8
Classifier: Topic :: Database
Classifier: Topic :: Software Development :: Libraries
Classifier: Topic :: Software Development :: Libraries :: Application Frameworks
Classifier: Topic :: Software Development :: Libraries :: Python Modules
Classifier: Topic :: System :: Distributed Computing
Classifier: Topic :: Utilities
Requires-Python: >=3.7
Requires-Dist: attrs
Requires-Dist: gino
Requires-Dist: SQLAlchemy
Provides-Extra: testing
Requires-Dist: mypy ; extra == 'testing'
Requires-Dist: flake8 ; extra == 'testing'
Requires-Dist: pytest ; extra == 'testing'
